markitup/__init__.py
markitup/doc.py
markitup/dtype.py
markitup/render.py
markitup/text.py
markitup/exception/__init__.py
markitup/exception/base.py
markitup/exception/html.py
markitup/html/__init__.py
markitup/html/elem.py
markitup/html/spec.py
markitup/html/text.py
markitup/md/__init__.py
markitup/md/elem.py
markitup/md/parse.py
MarkItUp-0.0.0.dev9.dist-info/METADATA
MarkItUp-0.0.0.dev9.dist-info/WHEEL
MarkItUp-0.0.0.dev9.dist-info/top_level.txt
MarkItUp-0.0.0.dev9.dist-info/RECORD
