Metadata-Version: 2.1
Name: MarkItUp
Version: 0.0.0.dev9
Requires-Python: >=3.10
Requires-Dist: IPython
Requires-Dist: pyserials
